deploy/deploy.py
ndtkit_api/NDTKitAScanInterface.py
ndtkit_api/NDTKitBScansInterface.py
ndtkit_api/NDTKitCScanInterface.py
ndtkit_api/NDTKitCartographyFrameInterface.py
ndtkit_api/NDTKitDefectDetectionInterface.py
ndtkit_api/NDTKitDimensionInterface.py
ndtkit_api/NDTKitROIInterface.py
ndtkit_api/NIFileConstants.py
ndtkit_api/enum_wrapper.py
ndtkit_api/ndtkit_socket_connection.py
ndtkit_api/py4j_utils.py
ndtkit_api/config/config.py
ndtkit_api/model/NIEnumDefectShapeType.py
ndtkit_api/model/NIEnumSpecialValue.py
ndtkit_api/model/ascan/NIAScanConfiguration.py
ndtkit_api/model/ascan/NIAScanGate.py
ndtkit_api/model/flaw/BooleanMember.py
ndtkit_api/model/flaw/CADInformation.py
ndtkit_api/model/flaw/DataStatistics.py
ndtkit_api/model/flaw/DefectGeometricInfos.py
ndtkit_api/model/flaw/DistancesToLayouts.py
ndtkit_api/model/flaw/Flaw.py
ndtkit_api/model/flaw/NIEnumDefectCharacteristics.py
ndtkit_api/model/frame/NICartographyFrame.py
ndtkit_api/model/frame/NICartographyFrameAScan.py
ndtkit_api/model/frame/NICartographyFrameCScan.py
ndtkit_api/model/frame/ScanType.py
ndtkit_api/model/framecomponents/palette/NIColorPalette.py
ndtkit_api/model/readers/NIEmptyReaderParameters.py
ndtkit_api/model/readers/NIEnumAmplitudeSign.py
ndtkit_api/model/readers/NIEnumGateMode.py
ndtkit_api/model/readers/NIEnumOverlapMethod.py
ndtkit_api/model/readers/NIReaderParameters.py
ndtkit_api/model/readers/isqus/NIISQUSReaderParameters.py
ndtkit_api/model/roi/EnumShapeSelection.py
ndtkit_api/model/roi/NIEnumRoiFormat.py
ndtkit_api/model/roi/NIEnumRoiGeometry.py
ndtkit_api/model/roi/NIRoi.py
ndtkit_api/model/roi/NIRoiLayout.py
ndtkit_api/model/roi/NIRoiMask.py
ndtkit_api/model/roi/NIRoiSelection.py
ndtkit_api/model/roi/Shape.py
ndtkit_api/model/scans/ascan/NIAScan.py
ndtkit_api-0.0.21.dist-info/licenses/LICENSE
ndtkit_api-0.0.21.dist-info/METADATA
ndtkit_api-0.0.21.dist-info/WHEEL
ndtkit_api-0.0.21.dist-info/entry_points.txt
ndtkit_api-0.0.21.dist-info/top_level.txt
ndtkit_api-0.0.21.dist-info/RECORD
