Metadata-Version: 2.4
Name: ndtkit_api
Version: 0.0.21
Summary: This Python API provides a high-level interface to interact with the NDTkit desktop application. It allows developers to script and automate NDTkit features remotely, leveraging the full power of the underlying Java application through a simple and pythonic library.
Author-email: Cédric BERTRAND <cedric.bertrand@testia.com>
License: Copyright (c) 2025 TESTIA SAS. All Rights Reserved.
Classifier: Programming Language :: Python :: 3
Classifier: Operating System :: OS Independent
Classifier: Intended Audience :: Developers
Classifier: Topic :: Software Development
Requires-Python: >=3.10
License-File: LICENSE
Requires-Dist: requests
Requires-Dist: py4j
Requires-Dist: pyinstaller
Dynamic: license-file
